tablespam/Excel/__init__.py
tablespam/Excel/_as_excel/__init__.py
tablespam/Excel/_as_excel/as_excel.py
tablespam/Excel/_as_excel/create_test_files.py
tablespam/Excel/_as_excel/locations.py
tablespam/Excel/_as_excel/styles.py
tablespam/Excel/_as_excel/write_excel.py
tablespam/Excel/xlsx_styles.py
tablespam/GT/__init__.py
tablespam/GT/_as_gt/__init__.py
tablespam/GT/_as_gt/as_gt.py
tablespam/GT/formatting.py
tablespam/TableSpam.py
tablespam/_Formula/Entry.py
tablespam/_Formula/Formulas.py
tablespam/_Formula/__init__.py
tablespam/__init__.py
tablespam/_as_string/__init__.py
tablespam/_as_string/as_string.py
tablespam-0.1.1.dist-info/LICENSE.md
tablespam-0.1.1.dist-info/METADATA
tablespam-0.1.1.dist-info/WHEEL
tablespam-0.1.1.dist-info/RECORD
