Metadata-Version: 2.3
Name: tablespam
Version: 0.1.1
Summary: 
License: GPL-3.0-or-later
Author: Jannik Orzek
Author-email: jannik.orzek@mailbox.org
Requires-Python: >=3.11,<4.0
Classifier: License :: OSI Approved :: GNU General Public License v3 or later (GPLv3+)
Classifier: Programming Language :: Python :: 3
Classifier: Programming Language :: Python :: 3.11
Classifier: Programming Language :: Python :: 3.12
Classifier: Programming Language :: Python :: 3.13
Requires-Dist: great-tables (>=0.15.0,<0.16.0)
Requires-Dist: numpy (>=2.2.1,<3.0.0)
Requires-Dist: openpyxl (>=3.1.5,<4.0.0)
Requires-Dist: polars (>=1.17.1,<2.0.0)
Requires-Dist: pyparsing (>=3.2.0,<4.0.0)
